airflow/providers/postgres/LICENSE
airflow/providers/postgres/__init__.py
airflow/providers/postgres/get_provider_info.py
airflow/providers/postgres/hooks/__init__.py
airflow/providers/postgres/hooks/postgres.py
airflow/providers/postgres/operators/__init__.py
airflow/providers/postgres/operators/postgres.py
apache_airflow_providers_postgres-5.9.0.dist-info/entry_points.txt
apache_airflow_providers_postgres-5.9.0.dist-info/WHEEL
apache_airflow_providers_postgres-5.9.0.dist-info/METADATA
apache_airflow_providers_postgres-5.9.0.dist-info/RECORD
