Metadata-Version: 2.1
Name: apache-airflow-providers-postgres
Version: 5.9.0
Summary: Provider package apache-airflow-providers-postgres for Apache Airflow
Keywords: airflow-provider,postgres,airflow,integration
Author-email: Apache Software Foundation <dev@airflow.apache.org>
Maintainer-email: Apache Software Foundation <dev@airflow.apache.org>
Requires-Python: ~=3.8
Classifier: Development Status :: 5 - Production/Stable
Classifier: Environment :: Console
Classifier: Environment :: Web Environment
Classifier: Intended Audience :: Developers
Classifier: Intended Audience :: System Administrators
Classifier: Framework :: Apache Airflow
Classifier: Framework :: Apache Airflow :: Provider
Classifier: License :: OSI Approved :: Apache Software License
Classifier: Programming Language :: Python :: 3.8
Classifier: Programming Language :: Python :: 3.9
Classifier: Programming Language :: Python :: 3.10
Classifier: Programming Language :: Python :: 3.11
Classifier: Topic :: System :: Monitoring
Requires-Dist: apache-airflow-providers-common-sql>=1.3.1
Requires-Dist: apache-airflow>=2.6.0
Requires-Dist: psycopg2-binary>=2.8.0
Requires-Dist: apache-airflow-providers-amazon>=2.6.0 ; extra == "amazon"
Requires-Dist: apache-airflow-providers-common-sql ; extra == "common.sql"
Requires-Dist: apache-airflow-providers-openlineage ; extra == "openlineage"
Project-URL: Bug Tracker, https://github.com/apache/airflow/issues
Project-URL: Changelog, https://airflow.apache.org/docs/apache-airflow-providers-postgres/5.9.0/changelog.html
Project-URL: Documentation, https://airflow.apache.org/docs/apache-airflow-providers-postgres/5.9.0
Project-URL: Slack Chat, https://s.apache.org/airflow-slack
Project-URL: Source Code, https://github.com/apache/airflow
Project-URL: Twitter, https://twitter.com/ApacheAirflow
Project-URL: YouTube, https://www.youtube.com/channel/UCSXwxpWZQ7XZ1WL3wqevChA/
Provides-Extra: amazon
Provides-Extra: common.sql
Provides-Extra: openlineage
